bia_integrator_api/__init__.py
bia_integrator_api/api/__init__.py
bia_integrator_api/api/private_api.py
bia_integrator_api/api/public_api.py
bia_integrator_api/api_client.py
bia_integrator_api/api_response.py
bia_integrator_api/configuration.py
bia_integrator_api/docs/Alias.md
bia_integrator_api/docs/AnnotationState.md
bia_integrator_api/docs/AuthenticationToken.md
bia_integrator_api/docs/Author.md
bia_integrator_api/docs/BIACollection.md
bia_integrator_api/docs/BIAImage.md
bia_integrator_api/docs/BIAImageAlias.md
bia_integrator_api/docs/BIAImageInput.md
bia_integrator_api/docs/BIAImageOmeMetadata.md
bia_integrator_api/docs/BIAImageOutput.md
bia_integrator_api/docs/BIAImageRepresentation.md
bia_integrator_api/docs/BIAImageRepresentationInput.md
bia_integrator_api/docs/BIAImageRepresentationOutput.md
bia_integrator_api/docs/BIAStudy.md
bia_integrator_api/docs/BIAStudyInput.md
bia_integrator_api/docs/BIAStudyOutput.md
bia_integrator_api/docs/Biosample.md
bia_integrator_api/docs/BiosampleAnnotation.md
bia_integrator_api/docs/BodyRegisterUser.md
bia_integrator_api/docs/BodySearchFileReferencesExactMatch.md
bia_integrator_api/docs/BodySearchImages.md
bia_integrator_api/docs/BodySearchImagesExactMatch.md
bia_integrator_api/docs/BodySearchStudiesExactMatch.md
bia_integrator_api/docs/BulkOperationItem.md
bia_integrator_api/docs/BulkOperationResponse.md
bia_integrator_api/docs/ChannelRendering.md
bia_integrator_api/docs/CollectionAnnotation.md
bia_integrator_api/docs/FileReference.md
bia_integrator_api/docs/FileReferenceAnnotation.md
bia_integrator_api/docs/HTTPValidationError.md
bia_integrator_api/docs/ImageAcquisition.md
bia_integrator_api/docs/ImageAcquisitionAnnotation.md
bia_integrator_api/docs/ImageAnnotation.md
bia_integrator_api/docs/LocationInner.md
bia_integrator_api/docs/ModelMetadata.md
bia_integrator_api/docs/Name.md
bia_integrator_api/docs/ObjectInfo.md
bia_integrator_api/docs/OmeMetadatSource.md
bia_integrator_api/docs/OriginalRelpath.md
bia_integrator_api-0.3.0.dist-info/WHEEL
bia_integrator_api-0.3.0.dist-info/METADATA
bia_integrator_api-0.3.0.dist-info/RECORD
